{"stats":{"minecraft:dropped":{"minecraft:gray_wool":1,"minecraft:wheat_seeds":2,"tombstone:grave_dust":2,"minecraft:warped_roots":1,"minecraft:dandelion":1},"minecraft:mined":{"minecraft:furnace":1,"minecraft:torch":1,"minecraft:grass":4,"minecraft:grass_block":2,"minecraft:bookshelf":1,"minecraft:dirt":1,"minecraft:glass":1,"minecraft:oak_leaves":2},"minecraft:used":{"tombstone:easter_egg":1,"farmersdelight:iron_knife":27,"minecraft:dark_oak_planks":2,"minecraft:black_wool":1,"minecraft:apple":2,"minecraft:bread":16,"minecraft:iron_pickaxe":1,"artifacts:eternal_steak":1,"minecraft:shield":4,"artifacts:everlasting_beef":2,"minecraft:bow":5,"minecraft:red_bed":1,"minecraft:furnace":1,"tombstone:gift":1,"minecraft:white_bed":1,"minecraft:gray_wool":1},"minecraft:picked_up":{"minecraft:book":3,"minecraft:torch":1,"minecraft:dandelion":1,"minecraft:potato":3,"tombstone:grave_dust":3,"minecraft:white_bed":2,"minecraft:dark_oak_log":10,"minecraft:red_bed":1,"minecraft:bone":2,"minecraft:wheat_seeds":2,"minecraft:gray_wool":2,"minecraft:black_wool":1,"minecraft:mutton":3,"minecraft:stick":2,"minecraft:furnace":1},"minecraft:killed_by":{"born_in_chaos_v1:baby_spider":1,"minecraft:zombie":1},"minecraft:killed":{"minecraft:sheep":2,"minecraft:chicken":1,"born_in_chaos_v1:baby_skeleton":1},"minecraft:custom":{"minecraft:time_since_rest":12256,"minecraft:waystone_activated":2,"lootr:looted_stat":44,"minecraft:interact_with_furnace":23,"minecraft:sprint_one_cm":183747,"minecraft:damage_taken":1973,"minecraft:walk_one_cm":184574,"minecraft:damage_blocked_by_shield":120,"minecraft:mob_kills":4,"minecraft:drop":6,"minecraft:damage_dealt":520,"minecraft:traded_with_villager":2,"minecraft:interact_with_crafting_table":16,"minecraft:talked_to_villager":13,"minecraft:fly_one_cm":859898,"minecraft:open_barrel":3,"minecraft:open_chest":17,"minecraft:crouch_one_cm":1225,"minecraft:play_time":62469,"tombstone:undead_killed":1,"minecraft:deaths":3,"minecraft:sneak_time":1976,"minecraft:walk_under_water_one_cm":12606,"minecraft:jump":1151,"minecraft:leave_game":2,"minecraft:time_since_death":12230,"minecraft:walk_on_water_one_cm":10348,"minecraft:sleep_in_bed":6,"minecraft:climb_one_cm":703,"minecraft:interact_with_smoker":1,"minecraft:total_world_time":62469,"minecraft:fall_one_cm":38370},"minecraft:crafted":{"artifacts:eternal_steak":1,"minecraft:bow":1,"minecraft:shield":1,"tombstone:grave_key":1,"minecraft:stick":4,"minecraft:iron_pickaxe":1,"minecraft:dark_oak_planks":40,"minecraft:enchanted_book":1}},"DataVersion":3465}